sprite_detection_module_masternhat/__init__.py
sprite_detection_module_masternhat/spriteutil.py
sprite_detection_module_masternhat-1.0.1.dist-info/LICENSE.md
sprite_detection_module_masternhat-1.0.1.dist-info/METADATA
sprite_detection_module_masternhat-1.0.1.dist-info/WHEEL
sprite_detection_module_masternhat-1.0.1.dist-info/top_level.txt
sprite_detection_module_masternhat-1.0.1.dist-info/RECORD
