Metadata-Version: 2.1
Name: sprite-detection-module-masternhat
Version: 1.0.1
Summary: Sprite detection package
Home-page: https://github.com/intek-training-jsc/sprite-detection-masternhat
Author: Le Quang Nhat
Author-email: nhat.le@f4.intek.edu.vn
License: MIT
Platform: UNKNOWN
Classifier: Programming Language :: Python :: 3
Classifier: License :: OSI Approved :: MIT License
Classifier: Operating System :: OS Independent
Requires-Python: >=3.6
Requires-Dist: numpy
Requires-Dist: pillow
